sleep_parameters/__init__.py
sleep_parameters/sn_sleep_parameters_class.py
sleep_parameters/tests/test_sn_run_sleep_parameters_class.py
sleep_parameters-0.1.0.dist-info/LICENSE
sleep_parameters-0.1.0.dist-info/WHEEL
sleep_parameters-0.1.0.dist-info/METADATA
sleep_parameters-0.1.0.dist-info/RECORD
